dff.v
module dff(
    input clk,
    input reset,
    input d,
    output reg q
);

always @(posedge clk) begin
    if (reset)
        q <= 1'b0;
    else
        q <= d;
end

endmodule

tb_dff.v
module tb_dff;

reg clk;
reg reset;
reg d;
wire q;

dff uut (
    .clk(clk),
    .reset(reset),
    .d(d),
    .q(q)
);

always #5 clk = ~clk;

initial begin
    clk = 0;
    reset = 1;
    d = 0;

    #10 reset = 0;
    #10 d = 1;
    #10 d = 0;
    #10 d = 1;

    #20 $finish;
end

initial begin
    $dumpfile("dff.vcd");
    $dumpvars(0, tb_dff);
end

endmodule

dff.vcd
$date
	Tue Dec 30 18:05:29 2025
$end
$version
	Icarus Verilog
$end
$timescale
	1s
$end
$scope module tb_dff $end
$var wire 1 ! q $end
$var reg 1 " clk $end
$var reg 1 # d $end
$var reg 1 $ reset $end
$scope module uut $end
$var wire 1 " clk $end
$var wire 1 # d $end
$var wire 1 $ reset $end
$var reg 1 ! q $end
$upscope $end
$upscope $end
$enddefinitions $end
$comment Show the parameter values. $end
$dumpall
$end
#0
$dumpvars
1$
0#
0"
x!
$end
#5
0!
1"
#10
0"
0$
#15
1"
#20
0"
1#
#25
1!
1"
#30
0"
0#
#35
0!
1"
#40
0"
1#
#45
1!
1"
